IoTPy/__init__.py
IoTPy/_version.py
IoTPy/agent_types/__init__.py
IoTPy/agent_types/actuators_simple.py
IoTPy/agent_types/basics.py
IoTPy/agent_types/check_agent_parameter_types.py
IoTPy/agent_types/iot.py
IoTPy/agent_types/merge.py
IoTPy/agent_types/multi.py
IoTPy/agent_types/op.py
IoTPy/agent_types/sink.py
IoTPy/agent_types/sliding_window_with_startup.py
IoTPy/agent_types/source.py
IoTPy/agent_types/split.py
IoTPy/agent_types/timed_agent.py
IoTPy/concurrency/PikaPublisher.py
IoTPy/concurrency/PikaSubscriber.py
IoTPy/concurrency/__init__.py
IoTPy/concurrency/multicore.py
IoTPy/concurrency/multithread.py
IoTPy/concurrency/pika_publication_agent.py
IoTPy/concurrency/pika_subscribe_agent.py
IoTPy/concurrency/utils.py
IoTPy/core/__init__.py
IoTPy/core/agent.py
IoTPy/core/compute_engine.py
IoTPy/core/helper_control.py
IoTPy/core/stream.py
IoTPy/core/system_parameters.py
IoTPy/helper_functions/Buffer.py
IoTPy/helper_functions/__init__.py
IoTPy/helper_functions/incremental_buffer.py
IoTPy/helper_functions/json_to_csv.py
IoTPy/helper_functions/print_stream.py
IoTPy/helper_functions/recent_values.py
IoTPy/helper_functions/type.py
tests/__init__.py
tests/agent_types/__init__.py
tests/agent_types/agent_types_test.py
tests/agent_types/test_agent.py
tests/agent_types/test_basics.py
tests/agent_types/test_element.py
tests/agent_types/test_iot.py
tests/agent_types/test_list.py
tests/agent_types/test_merge.py
tests/agent_types/test_multi.py
tests/agent_types/test_shared_variables.py
tests/agent_types/test_sink.py
tests/agent_types/test_sliding_window_with_startup.py
tests/agent_types/test_split.py
tests/agent_types/test_timed_agent.py
tests/agent_types/test_window.py
tests/concurrency/__init__.py
tests/concurrency/test_lock.py
tests/concurrency/test_multicore.py
tests/concurrency/test_multicore37.py
tests/concurrency/test_multithread.py
tests/distributed/CloudAMQP_test.py
tests/distributed/__init__.py
tests/distributed/emit_log_direct.py
tests/distributed/pika_publisher_test.py
IoTPy-1.1.0.dist-info/LICENSE
IoTPy-1.1.0.dist-info/METADATA
IoTPy-1.1.0.dist-info/WHEEL
IoTPy-1.1.0.dist-info/top_level.txt
IoTPy-1.1.0.dist-info/RECORD
